odoo/addons/product_logistics_uom_total_weight/README.rst
odoo/addons/product_logistics_uom_total_weight/__init__.py
odoo/addons/product_logistics_uom_total_weight/__manifest__.py
odoo/addons/product_logistics_uom_total_weight/i18n/ca.po
odoo/addons/product_logistics_uom_total_weight/i18n/es.po
odoo/addons/product_logistics_uom_total_weight/i18n/it.po
odoo/addons/product_logistics_uom_total_weight/i18n/product_logistics_uom_total_weight.pot
odoo/addons/product_logistics_uom_total_weight/models/__init__.py
odoo/addons/product_logistics_uom_total_weight/models/product.py
odoo/addons/product_logistics_uom_total_weight/readme/CONTRIBUTORS.md
odoo/addons/product_logistics_uom_total_weight/readme/DESCRIPTION.md
odoo/addons/product_logistics_uom_total_weight/readme/USAGE.md
odoo/addons/product_logistics_uom_total_weight/static/description/icon.png
odoo/addons/product_logistics_uom_total_weight/static/description/icon.svg
odoo/addons/product_logistics_uom_total_weight/static/description/index.html
odoo/addons/product_logistics_uom_total_weight/tests/__init__.py
odoo/addons/product_logistics_uom_total_weight/tests/test_product_weight.py
odoo/addons/product_logistics_uom_total_weight/views/product_views.xml
odoo_addon_product_logistics_uom_total_weight-17.0.1.0.0.4.dist-info/METADATA
odoo_addon_product_logistics_uom_total_weight-17.0.1.0.0.4.dist-info/WHEEL
odoo_addon_product_logistics_uom_total_weight-17.0.1.0.0.4.dist-info/top_level.txt
odoo_addon_product_logistics_uom_total_weight-17.0.1.0.0.4.dist-info/RECORD
